{
    ".public": "public/",
    ".entrypoints": {
        "critical": [
            "public/includes/chunk.65a639fb78fb561b79ec.js",
            "public/includes/extract.25.d0f92d0cbc80c751241a.css",
            "public/includes/entry.d0f92d0cbc80c751241a.js"
        ],
        "polyfill": [
            "public/includes/entry.283051bbabbd5d8542ac.js"
        ],
        "client": [
            "public/includes/chunk.65a639fb78fb561b79ec.js",
            "public/includes/entry.5d00ba283d55c8be0df3.js"
        ],
        "__KOOT__CLIENT__RUN__FIRST__": [
            "public/includes/chunk.65a639fb78fb561b79ec.js",
            "public/includes/entry.a40b8ee6d51d95098891.js"
        ]
    },
    ".files": {
        "Equipment Details~Home~People~People Details~Ship Details~Ship List.js": "public/includes/chunk.c07657e344a2187431f0.js",
        "Arsenal~Equipments~Fleet Builder (WIP)~TP Calculator.js": "public/includes/chunk.5d02fd5dc44e3234b6be.js",
        "Equipment Details~People Details~Ship Details~Ship List.js": "public/includes/chunk.7854d1cb2865aaf28660.js",
        "commons.js": "public/includes/chunk.65a639fb78fb561b79ec.js",
        "Arsenal~Equipment Details.js": "public/includes/chunk.a9aee043fb2564d5677b.js",
        "vendors~Home~Ship Details.js": "public/includes/chunk.adf80598e39bb480478b.js",
        "About.js": "public/includes/chunk.b9bd2606c6ea9527418a.js",
        "Academy.js": "public/includes/chunk.a027e79e8b30b200c3f4.js",
        "Arsenal.js": "public/includes/chunk.71119c05d9a6c70d1e12.js",
        "Equipment Details.js": "public/includes/chunk.e0e4b11111ad15dbc9a4.js",
        "Equipments.js": "public/includes/chunk.da864f97276566f036fc.js",
        "Ex-CGs.js": "public/includes/chunk.4ca1e0cd6fd4d07699a6.js",
        "Expeditions.js": "public/includes/chunk.0f0e660e1c780f2f3f5f.js",
        "Fleet Builder.js": "public/includes/chunk.55b9c612b2fe283cfe84.js",
        "Fleet Builder (WIP).js": "public/includes/chunk.c877352d85b42a79250e.js",
        "Fleet Builder Fleet Details.js": "public/includes/chunk.cb26df79f3fff1a82865.js",
        "Home.js": "public/includes/chunk.21ed33ad371e97e548a9.js",
        "People.js": "public/includes/chunk.2bc0b8ba9568e2b192f9.js",
        "People Details.js": "public/includes/chunk.de6b1a76fe1b094ec48d.js",
        "Ship Details.css": "public/includes/extract.19.2459c02a8e9364b5e127.css",
        "Ship Details.js": "public/includes/chunk.2459c02a8e9364b5e127.js",
        "Ship List.js": "public/includes/chunk.ab67d9aaa1d1aaeab3d6.js",
        "Sorties.js": "public/includes/chunk.a94ef967f8ca0e608112.js",
        "TP Calculator.js": "public/includes/chunk.9b2d2c3b428418a5b42a.js",
        "__KOOT__CLIENT__RUN__FIRST__.js": "public/includes/entry.a40b8ee6d51d95098891.js",
        "client.js": "public/includes/entry.5d00ba283d55c8be0df3.js",
        "critical.css": "public/includes/extract.25.d0f92d0cbc80c751241a.css",
        "critical.js": "public/includes/entry.d0f92d0cbc80c751241a.js",
        "polyfill.js": "public/includes/entry.283051bbabbd5d8542ac.js",
        "vendors~Ship Details.css": "public/includes/extract.27.ee16248218ecee37840e.css",
        "vendors~Ship Details.js": "public/includes/chunk.ee16248218ecee37840e.js",
        "vendors~nedb.js": "public/includes/chunk.3897f138963b15d77b11.js",
        "__KOOT__EXTRACT__CSS__.css": "public/includes/extract.all.7499c4ae23916c222d5af89f944f591c.css"
    },
    "service-worker": [
        "public/service-worker.js"
    ]
}