{
    ".entrypoints": {
        "critical": [
            "public/includes/chunk.2597f6fd4bb9ca07dcaa.js",
            "public/includes/extract.26.5bb80e87eb9943326de4.css",
            "public/includes/entry.5bb80e87eb9943326de4.js"
        ],
        "polyfill": [
            "public/includes/chunk.2597f6fd4bb9ca07dcaa.js",
            "public/includes/entry.82ae670dd08972690af6.js"
        ],
        "client": [
            "public/includes/chunk.2597f6fd4bb9ca07dcaa.js",
            "public/includes/entry.14678615764258f55122.js"
        ]
    },
    ".files": {
        "DEV. Components~Equipment Details~People~People Details~Ship Details~Ship List.js": "public/includes/chunk.9bb5e864d0a53562e8c0.js",
        "DEV. Components~Equipment Details~People Details~Ship Details~Ship List.js": "public/includes/chunk.7c9cb30c0e67c2695250.js",
        "Arsenal~Equipments~Fleet Builder (WIP)~TP Calculator.js": "public/includes/chunk.0d73d12462f3c160c6ed.js",
        "Arsenal~Equipment Details~Ship Details.js": "public/includes/chunk.ab68c2735deb1bd15674.js",
        "commons.js": "public/includes/chunk.2597f6fd4bb9ca07dcaa.js",
        "About.js": "public/includes/chunk.ef4650c680e1dccb6b8f.js",
        "Academy.js": "public/includes/chunk.77d2f666b2dc9d5a3661.js",
        "Arsenal.js": "public/includes/chunk.da8a9c4d2387f714de3f.js",
        "DEV. Components.js": "public/includes/chunk.413a866687982a3a7f27.js",
        "DEV. Icons.js": "public/includes/chunk.5f0d3e4eed24a1bb42cf.js",
        "DEV. Lorem-ipsum.js": "public/includes/chunk.eae9a60754ed93293a58.js",
        "Equipment Details.js": "public/includes/chunk.7f657b916e424ab87c37.js",
        "Equipments.js": "public/includes/chunk.bb5c5817b54c9a4c4867.js",
        "Ex-CGs.js": "public/includes/chunk.921cc7f1472fb3264116.js",
        "Expeditions.js": "public/includes/chunk.393d9331c0e8985db4c9.js",
        "Fleet Builder.js": "public/includes/chunk.511b0946f84afe13e2d7.js",
        "Fleet Builder (WIP).js": "public/includes/chunk.cf0489f65fa7413cd48e.js",
        "Fleet Builder Fleet Details.js": "public/includes/chunk.8fb21dfdb27c7ac72cb0.js",
        "Home.js": "public/includes/chunk.3186005f151ddf6cbcdc.js",
        "People.js": "public/includes/chunk.f5493756947dac4e6813.js",
        "People Details.js": "public/includes/chunk.7cc7c52f0a3e686518a6.js",
        "Ship Details.js": "public/includes/chunk.9126c009c6a175fb107f.js",
        "Ship List.js": "public/includes/chunk.682d814a6ba268f01e54.js",
        "Sorties.js": "public/includes/chunk.ac7b1f6b887df50f0929.js",
        "TP Calculator.js": "public/includes/chunk.5689a92320686f9b05df.js",
        "client.js": "public/includes/entry.14678615764258f55122.js",
        "critical.css": "public/includes/extract.26.5bb80e87eb9943326de4.css",
        "critical.js": "public/includes/entry.5bb80e87eb9943326de4.js",
        "polyfill.js": "public/includes/entry.82ae670dd08972690af6.js",
        "vendors~Home.js": "public/includes/chunk.e3b5ede1354c97e69cd9.js",
        "vendors~Ship Details.js": "public/includes/chunk.a4787e240f6113e2318b.js",
        "vendors~nedb.js": "public/includes/chunk.f58a89d3ff5cef0dfb1d.js",
        "__KOOT__EXTRACT__CSS__.css": "public/includes/extract.all.045c6281457680f8bad8bdf65fd72047.css"
    },
    "DEV. Components~Equipment Details~People~People Details~Ship Details~Ship List": [
        "public/includes/chunk.9bb5e864d0a53562e8c0.js"
    ],
    "DEV. Components~Equipment Details~People Details~Ship Details~Ship List": [
        "public/includes/chunk.7c9cb30c0e67c2695250.js"
    ],
    "Arsenal~Equipments~Fleet Builder (WIP)~TP Calculator": [
        "public/includes/chunk.0d73d12462f3c160c6ed.js"
    ],
    "Arsenal~Equipment Details~Ship Details": [
        "public/includes/chunk.ab68c2735deb1bd15674.js"
    ],
    "commons": [
        "public/includes/chunk.2597f6fd4bb9ca07dcaa.js"
    ],
    "About": [
        "public/includes/chunk.ef4650c680e1dccb6b8f.js"
    ],
    "Academy": [
        "public/includes/chunk.77d2f666b2dc9d5a3661.js"
    ],
    "Arsenal": [
        "public/includes/chunk.da8a9c4d2387f714de3f.js"
    ],
    "DEV. Components": [
        "public/includes/chunk.413a866687982a3a7f27.js"
    ],
    "DEV. Icons": [
        "public/includes/chunk.5f0d3e4eed24a1bb42cf.js"
    ],
    "DEV. Lorem-ipsum": [
        "public/includes/chunk.eae9a60754ed93293a58.js"
    ],
    "Equipment Details": [
        "public/includes/chunk.7f657b916e424ab87c37.js"
    ],
    "Equipments": [
        "public/includes/chunk.bb5c5817b54c9a4c4867.js"
    ],
    "Ex-CGs": [
        "public/includes/chunk.921cc7f1472fb3264116.js"
    ],
    "Expeditions": [
        "public/includes/chunk.393d9331c0e8985db4c9.js"
    ],
    "Fleet Builder": [
        "public/includes/chunk.511b0946f84afe13e2d7.js"
    ],
    "Fleet Builder (WIP)": [
        "public/includes/chunk.cf0489f65fa7413cd48e.js"
    ],
    "Fleet Builder Fleet Details": [
        "public/includes/chunk.8fb21dfdb27c7ac72cb0.js"
    ],
    "Home": [
        "public/includes/chunk.3186005f151ddf6cbcdc.js"
    ],
    "People": [
        "public/includes/chunk.f5493756947dac4e6813.js"
    ],
    "People Details": [
        "public/includes/chunk.7cc7c52f0a3e686518a6.js"
    ],
    "Ship Details": [
        "public/includes/chunk.9126c009c6a175fb107f.js"
    ],
    "Ship List": [
        "public/includes/chunk.682d814a6ba268f01e54.js"
    ],
    "Sorties": [
        "public/includes/chunk.ac7b1f6b887df50f0929.js"
    ],
    "TP Calculator": [
        "public/includes/chunk.5689a92320686f9b05df.js"
    ],
    "client": [
        "public/includes/entry.14678615764258f55122.js"
    ],
    "critical": [
        "public/includes/extract.26.5bb80e87eb9943326de4.css",
        "public/includes/entry.5bb80e87eb9943326de4.js"
    ],
    "polyfill": [
        "public/includes/entry.82ae670dd08972690af6.js"
    ],
    "vendors~Home": [
        "public/includes/chunk.e3b5ede1354c97e69cd9.js"
    ],
    "vendors~Ship Details": [
        "public/includes/chunk.a4787e240f6113e2318b.js"
    ],
    "vendors~nedb": [
        "public/includes/chunk.f58a89d3ff5cef0dfb1d.js"
    ],
    "__KOOT__EXTRACT__CSS__": [
        "public/includes/extract.all.045c6281457680f8bad8bdf65fd72047.css"
    ],
    "service-worker": [
        "public/service-worker.js"
    ]
}